module2-mbist/rtl/sram_256x8.v
// Sky130 SRAM Memory Subsystem — Module 2
// Behavioral 256x8 SRAM with fault injection
// Synchronous write, always-on combinational read

module sram_256x8 #(
    parameter SAF_ADDR = -1,
    parameter SAF_BIT  =  0,
    parameter SAF_VAL  =  0,
    parameter TF_ADDR  = -1,
    parameter TF_BIT   =  0,
    parameter TF_DIR   =  0,
    parameter CF_AGG   = -1,
    parameter CF_VIC   = -1,
    parameter CF_BIT   =  0
)(
    input            clk,
    input            ce,
    input            we,
    input      [7:0] addr,
    input      [7:0] din,
    output     [7:0] dout
);

    reg [7:0] mem [0:255];
    reg [7:0] prev_val;
    integer i;

    initial begin
        for (i = 0; i < 256; i = i + 1)
            mem[i] = 8'h00;
    end

    // Synchronous write
    always @(posedge clk) begin
        if (ce && we) begin
            prev_val    = mem[addr];
            mem[addr]  <= din;

            // Transition fault
            if (TF_ADDR >= 0 && addr == TF_ADDR[7:0]) begin
                if (TF_DIR == 0 &&
                    prev_val[TF_BIT] == 1'b0 &&
                    din[TF_BIT]      == 1'b1)
                    mem[addr][TF_BIT] <= 1'b0;
                if (TF_DIR == 1 &&
                    prev_val[TF_BIT] == 1'b1 &&
                    din[TF_BIT]      == 1'b0)
                    mem[addr][TF_BIT] <= 1'b1;
            end

            // Coupling fault
            if (CF_AGG >= 0 && addr == CF_AGG[7:0] && CF_VIC >= 0)
                mem[CF_VIC[7:0]][CF_BIT] <= ~mem[CF_VIC[7:0]][CF_BIT];
        end
    end

    // Combinational read — always outputs mem[addr]
    reg [7:0] dout_raw;

    always @(*) begin
        dout_raw = mem[addr];
        if (SAF_ADDR >= 0 && addr == SAF_ADDR[7:0]) begin
            if (SAF_VAL == 0)
                dout_raw = mem[addr] & ~(8'h01 << SAF_BIT);
            else
                dout_raw = mem[addr] |  (8'h01 << SAF_BIT);
        end
    end

    assign dout = dout_raw;

endmodule

module2-mbist/rtl/mbist_ctrl.v
// Sky130 SRAM Memory Subsystem — Module 2
// March C- MBIST Controller
// Fix: 2-bit phase for proper write timing
// phase=0: issue read
// phase=1: latch dout + check + setup write (addr stable)
// phase=2: write fires, then increment/decrement addr

module mbist_ctrl (
    input            clk,
    input            rst,
    input            start,
    input      [7:0] mem_dout,
    output reg [7:0] mem_addr,
    output reg [7:0] mem_din,
    output reg       mem_we,
    output reg       mem_ce,
    output reg       done,
    output reg       pass_fail,
    output reg [7:0] diag_addr
);

    localparam IDLE = 3'd0;
    localparam E0   = 3'd1;
    localparam E1   = 3'd2;
    localparam E2   = 3'd3;
    localparam E3   = 3'd4;
    localparam E4   = 3'd5;
    localparam DONE = 3'd6;

    reg [2:0] state;
    reg [1:0] phase;       // 2-bit phase
    reg       diag_captured;
    reg [7:0] read_data;

    // last address flag helpers
    wire at_top = (mem_addr == 8'hFF);
    wire at_bot = (mem_addr == 8'h00);

    always @(posedge clk) begin
        if (rst) begin
            state         <= IDLE;
            mem_addr      <= 8'h00;
            mem_din       <= 8'h00;
            mem_we        <= 1'b0;
            mem_ce        <= 1'b0;
            done          <= 1'b0;
            pass_fail     <= 1'b1;
            diag_addr     <= 8'hFF;
            diag_captured <= 1'b0;
            phase         <= 2'd0;
            read_data     <= 8'h00;
        end else begin
            case (state)

                // ----------------------------------------
                IDLE: begin
                    done          <= 1'b0;
                    pass_fail     <= 1'b1;
                    diag_captured <= 1'b0;
                    if (start) begin
                        state    <= E0;
                        mem_addr <= 8'h00;
                        mem_din  <= 8'h00;
                        mem_we   <= 1'b1;
                        mem_ce   <= 1'b1;
                        phase    <= 2'd0;
                    end
                end

                // ----------------------------------------
                // E0: up(w0) — write 0 to all ascending
                // Simple: one cycle per address, we=1 always
                E0: begin
                    mem_we  <= 1'b1;
                    mem_ce  <= 1'b1;
                    mem_din <= 8'h00;
                    // Write fires at current addr this cycle
                    if (at_top) begin
                        state    <= E1;
                        mem_addr <= 8'h00;
                        mem_we   <= 1'b0;
                        phase    <= 2'd0;
                    end else begin
                        mem_addr <= mem_addr + 1;
                    end
                end

                // ----------------------------------------
                // E1: up(r0,w1)
                // phase=0: issue read (we=0)
                // phase=1: latch + check + setup write (addr stable)
                // phase=2: write fires, advance addr
                E1: begin
                    mem_ce <= 1'b1;
                    case (phase)
                        2'd0: begin
                            mem_we    <= 1'b0;
                            phase     <= 2'd1;
                        end
                        2'd1: begin
                            // latch read data
                            read_data <= mem_dout;
                            // setup write to same addr
                            mem_we    <= 1'b1;
                            mem_din   <= 8'hFF;
                            phase     <= 2'd2;
                        end
                        2'd2: begin
                            // write fired at current addr
                            // check latched read data
                            if (read_data !== 8'h00) begin
                                pass_fail <= 1'b0;
                                if (!diag_captured) begin
                                    diag_addr     <= mem_addr;
                                    diag_captured <= 1'b1;
                                end
                            end
                            mem_we <= 1'b0;
                            phase  <= 2'd0;
                            if (at_top) begin
                                state    <= E2;
                                mem_addr <= 8'h00;
                            end else begin
                                mem_addr <= mem_addr + 1;
                            end
                        end
                        default: phase <= 2'd0;
                    endcase
                end

                // ----------------------------------------
                // E2: up(r1,w0)
                E2: begin
                    mem_ce <= 1'b1;
                    case (phase)
                        2'd0: begin
                            mem_we <= 1'b0;
                            phase  <= 2'd1;
                        end
                        2'd1: begin
                            read_data <= mem_dout;
                            mem_we    <= 1'b1;
                            mem_din   <= 8'h00;
                            phase     <= 2'd2;
                        end
                        2'd2: begin
                            if (read_data !== 8'hFF) begin
                                pass_fail <= 1'b0;
                                if (!diag_captured) begin
                                    diag_addr     <= mem_addr;
                                    diag_captured <= 1'b1;
                                end
                            end
                            mem_we <= 1'b0;
                            phase  <= 2'd0;
                            if (at_top) begin
                                state    <= E3;
                                mem_addr <= 8'hFF;
                            end else begin
                                mem_addr <= mem_addr + 1;
                            end
                        end
                        default: phase <= 2'd0;
                    endcase
                end

                // ----------------------------------------
                // E3: down(r0,w1)
                E3: begin
                    mem_ce <= 1'b1;
                    case (phase)
                        2'd0: begin
                            mem_we <= 1'b0;
                            phase  <= 2'd1;
                        end
                        2'd1: begin
                            read_data <= mem_dout;
                            mem_we    <= 1'b1;
                            mem_din   <= 8'hFF;
                            phase     <= 2'd2;
                        end
                        2'd2: begin
                            if (read_data !== 8'h00) begin
                                pass_fail <= 1'b0;
                                if (!diag_captured) begin
                                    diag_addr     <= mem_addr;
                                    diag_captured <= 1'b1;
                                end
                            end
                            mem_we <= 1'b0;
                            phase  <= 2'd0;
                            if (at_bot) begin
                                state    <= E4;
                                mem_addr <= 8'hFF;
                            end else begin
                                mem_addr <= mem_addr - 1;
                            end
                        end
                        default: phase <= 2'd0;
                    endcase
                end

                // ----------------------------------------
                // E4: down(r1) — read only, two phases
                E4: begin
                    mem_ce <= 1'b1;
                    mem_we <= 1'b0;
                    case (phase)
                        2'd0: begin
                            phase <= 2'd1;
                        end
                        2'd1: begin
                            read_data <= mem_dout;
                            phase     <= 2'd2;
                        end
                        2'd2: begin
                            if (read_data !== 8'hFF) begin
                                pass_fail <= 1'b0;
                                if (!diag_captured) begin
                                    diag_addr     <= mem_addr;
                                    diag_captured <= 1'b1;
                                end
                            end
                            phase <= 2'd0;
                            if (at_bot) begin
                                state <= DONE;
                            end else begin
                                mem_addr <= mem_addr - 1;
                            end
                        end
                        default: phase <= 2'd0;
                    endcase
                end

                // ----------------------------------------
                DONE: begin
                    mem_ce <= 1'b0;
                    mem_we <= 1'b0;
                    done   <= 1'b1;
                end

            endcase
        end
    end

endmodule

module2-mbist/tb/tb_mbist_basic.v
// Testbench: MBIST controller + fault-free SRAM
// Expected result: pass_fail=1 (PASS), done=1

`timescale 1ns/1ps

module tb_mbist_basic;

    // ---- Clock and control signals ----
    reg clk;
    reg rst;
    reg start;

    // ---- MBIST controller outputs ----
    wire [7:0] mem_addr;
    wire [7:0] mem_din;
    wire       mem_we;
    wire       mem_ce;
    wire       done;
    wire       pass_fail;
    wire [7:0] diag_addr;

    // ---- SRAM output ----
    wire [7:0] mem_dout;

    // ---- Instantiate MBIST controller ----
    mbist_ctrl uut (
        .clk      (clk),
        .rst      (rst),
        .start    (start),
        .mem_dout (mem_dout),
        .mem_addr (mem_addr),
        .mem_din  (mem_din),
        .mem_we   (mem_we),
        .mem_ce   (mem_ce),
        .done     (done),
        .pass_fail(pass_fail),
        .diag_addr(diag_addr)
    );

    // ---- Instantiate fault-free SRAM ----
    // All fault parameters left at default (-1 = no fault)
    sram_256x8 #(
        .SAF_ADDR(-1),
        .TF_ADDR (-1),
        .CF_AGG  (-1)
    ) mem (
        .clk  (clk),
        .ce   (mem_ce),
        .we   (mem_we),
        .addr (mem_addr),
        .din  (mem_din),
        .dout (mem_dout)
    );

    // ---- Clock generation ----
    initial clk = 0;
    always #5 clk = ~clk; // 10ns period = 100MHz

    // ---- Timeout watchdog ----
    // March C- on 256x8 = ~5000 clock cycles
    // Timeout after 20000 cycles to catch infinite loops
    initial begin
        #200000;
        $display("TIMEOUT — simulation ran too long");
        $finish;
    end

    // ---- Test stimulus ----
    initial begin
        // Initialize
        rst   = 1;
        start = 0;

        // Hold reset for 3 clock cycles
        @(posedge clk); #1;
        @(posedge clk); #1;
        @(posedge clk); #1;

        // Release reset
        rst = 0;
        @(posedge clk); #1;

        // Pulse start for one clock cycle
        start = 1;
        @(posedge clk); #1;
        start = 0;

        // Wait for done signal
        @(posedge done);
        #10; // wait a bit after done

        // Report result
        $display("=================================");
        $display("MBIST Test Complete");
        $display("Result: %s", pass_fail ? "PASS" : "FAIL");
        $display("Diag addr: %0d", diag_addr);
        $display("=================================");

        if (pass_fail == 1'b1)
            $display("CORRECT: fault-free memory passed");
        else
            $display("ERROR: fault-free memory should PASS");

        $finish;
    end

    // ---- Optional waveform dump ----
    initial begin
        $dumpfile("tb_mbist_basic.vcd");
        $dumpvars(0, tb_mbist_basic);
    end

endmodule

module2-mbist/tb/tb_mbist_basic.vcd
$date
	Sun May 10 19:58:16 2026
$end
$version
	Icarus Verilog
$end
$timescale
	1ps
$end
$scope module tb_mbist_basic $end
$var wire 1 ! pass_fail $end
$var wire 1 " mem_we $end
$var wire 8 # mem_dout [7:0] $end
$var wire 8 $ mem_din [7:0] $end
$var wire 1 % mem_ce $end
$var wire 8 & mem_addr [7:0] $end
$var wire 1 ' done $end
$var wire 8 ( diag_addr [7:0] $end
$var reg 1 ) clk $end
$var reg 1 * rst $end
$var reg 1 + start $end
$scope module mem $end
$var wire 1 ) clk $end
$var wire 8 , dout [7:0] $end
$var wire 1 " we $end
$var wire 8 - din [7:0] $end
$var wire 1 % ce $end
$var wire 8 . addr [7:0] $end
$var reg 8 / dout_raw [7:0] $end
$var reg 8 0 prev_val [7:0] $end
$var integer 32 1 i [31:0] $end
$upscope $end
$scope module uut $end
$var wire 1 ) clk $end
$var wire 8 2 mem_dout [7:0] $end
$var wire 1 * rst $end
$var wire 1 + start $end
$var wire 1 3 at_top $end
$var wire 1 4 at_bot $end
$var reg 8 5 diag_addr [7:0] $end
$var reg 1 6 diag_captured $end
$var reg 1 ' done $end
$var reg 8 7 mem_addr [7:0] $end
$var reg 1 % mem_ce $end
$var reg 8 8 mem_din [7:0] $end
$var reg 1 " mem_we $end
$var reg 1 ! pass_fail $end
$var reg 2 9 phase [1:0] $end
$var reg 8 : read_data [7:0] $end
$var reg 3 ; state [2:0] $end
$upscope $end
$upscope $end
$enddefinitions $end
#0
$dumpvars
bx ;
bx :
bx 9
bx 8
bx 7
x6
bx 5
x4
x3
bx 2
b100000000 1
bx 0
bx /
bx .
bx -
bx ,
0+
1*
0)
bx (
x'
bx &
x%
bx $
bx #
x"
x!
$end
#5000
b0 #
b0 ,
b0 2
b0 /
b0 :
b0 9
06
b11111111 (
b11111111 5
1!
0'
0%
0"
b0 $
b0 -
b0 8
03
14
b0 &
b0 .
b0 7
b0 ;
1)
#10000
0)
#15000
1)
#20000
0)
#25000
1)
#26000
0*
#30000
0)
#35000
1)
#36000
1+
#40000
0)
#45000
1%
1"
b1 ;
1)
#46000
0+
#50000
0)
#55000
04
b1 &
b1 .
b1 7
b0 0
1)
#60000
0)
#65000
b10 &
b10 .
b10 7
1)
#70000
0)
#75000
b11 &
b11 .
b11 7
1)
#80000
0)
#85000
b100 &
b100 .
b100 7
1)
#90000
0)
#95000
b101 &
b101 .
b101 7
1)
#100000
0)
#105000
b110 &
b110 .
b110 7
1)
#110000
0)
#115000
b111 &
b111 .
b111 7
1)
#120000
0)
#125000
b1000 &
b1000 .
b1000 7
1)
#130000
0)
#135000
b1001 &
b1001 .
b1001 7
1)
#140000
0)
#145000
b1010 &
b1010 .
b1010 7
1)
#150000
0)
#155000
b1011 &
b1011 .
b1011 7
1)
#160000
0)
#165000
b1100 &
b1100 .
b1100 7
1)
#170000
0)
#175000
b1101 &
b1101 .
b1101 7
1)
#180000
0)
#185000
b1110 &
b1110 .
b1110 7
1)
#190000
0)
#195000
b1111 &
b1111 .
b1111 7
1)
#200000
0)
#205000
b10000 &
b10000 .
b10000 7
1)
#210000
0)
#215000
b10001 &
b10001 .
b10001 7
1)
#220000
0)
#225000
b10010 &
b10010 .
b10010 7
1)
#230000
0)
#235000
b10011 &
b10011 .
b10011 7
1)
#240000
0)
#245000
b10100 &
b10100 .
b10100 7
1)
#250000
0)
#255000
b10101 &
b10101 .
b10101 7
1)
#260000
0)
#265000
b10110 &
b10110 .
b10110 7
1)
#270000
0)
#275000
b10111 &
b10111 .
b10111 7
1)
#280000
0)
#285000
b11000 &
b11000 .
b11000 7
1)
#290000
0)
#295000
b11001 &
b11001 .
b11001 7
1)
#300000
0)
#305000
b11010 &
b11010 .
b11010 7
1)
#310000
0)
#315000
b11011 &
b11011 .
b11011 7
1)
#320000
0)
#325000
b11100 &
b11100 .
b11100 7
1)
#330000
0)
#335000
b11101 &
b11101 .
b11101 7
1)
#340000
0)
#345000
b11110 &
b11110 .
b11110 7
1)
#350000
0)
#355000
b11111 &
b11111 .
b11111 7
1)
#360000
0)
#365000
b100000 &
b100000 .
b100000 7
1)
#370000
0)
#375000
b100001 &
b100001 .
b100001 7
1)
#380000
0)
#385000
b100010 &
b100010 .
b100010 7
1)
#390000
0)
#395000
b100011 &
b100011 .
b100011 7
1)
#400000
0)
#405000
b100100 &
b100100 .
b100100 7
1)
#410000
0)
#415000
b100101 &
b100101 .
b100101 7
1)
#420000
0)
#425000
b100110 &
b100110 .
b100110 7
1)
#430000
0)
#435000
b100111 &
b100111 .
b100111 7
1)
#440000
0)
#445000
b101000 &
b101000 .
b101000 7
1)
#450000
0)
#455000
b101001 &
b101001 .
b101001 7
1)
#460000
0)
#465000
b101010 &
b101010 .
b101010 7
1)
#470000
0)
#475000
b101011 &
b101011 .
b101011 7
1)
#480000
0)
#485000
b101100 &
b101100 .
b101100 7
1)
#490000
0)
#495000
b101101 &
b101101 .
b101101 7
1)
#500000
0)
#505000
b101110 &
b101110 .
b101110 7
1)
#510000
0)
#515000
b101111 &
b101111 .
b101111 7
1)
#520000
0)
#525000
b110000 &
b110000 .
b110000 7
1)
#530000
0)
#535000
b110001 &
b110001 .
b110001 7
1)
#540000
0)
#545000
b110010 &
b110010 .
b110010 7
1)
#550000
0)
#555000
b110011 &
b110011 .
b110011 7
1)
#560000
0)
#565000
b110100 &
b110100 .
b110100 7
1)
#570000
0)
#575000
b110101 &
b110101 .
b110101 7
1)
#580000
0)
#585000
b110110 &
b110110 .
b110110 7
1)
#590000
0)
#595000
b110111 &
b110111 .
b110111 7
1)
#600000
0)
#605000
b111000 &
b111000 .
b111000 7
1)
#610000
0)
#615000
b111001 &
b111001 .
b111001 7
1)
#620000
0)
#625000
b111010 &
b111010 .
b111010 7
1)
#630000
0)
#635000
b111011 &
b111011 .
b111011 7
1)
#640000
0)
#645000
b111100 &
b111100 .
b111100 7
1)
#650000
0)
#655000
b111101 &
b111101 .
b111101 7
1)
#660000
0)
#665000
b111110 &
b111110 .
b111110 7
1)
#670000
0)
#675000
b111111 &
b111111 .
b111111 7
1)
#680000
0)
#685000
b1000000 &
b1000000 .
b1000000 7
1)
#690000
0)
#695000
b1000001 &
b1000001 .
b1000001 7
1)
#700000
0)
#705000
b1000010 &
b1000010 .
b1000010 7
1)
#710000
0)
#715000
b1000011 &
b1000011 .
b1000011 7
1)
#720000
0)
#725000
b1000100 &
b1000100 .
b1000100 7
1)
#730000
0)
#735000
b1000101 &
b1000101 .
b1000101 7
1)
#740000
0)
#745000
b1000110 &
b1000110 .
b1000110 7
1)
#750000
0)
#755000
b1000111 &
b1000111 .
b1000111 7
1)
#760000
0)
#765000
b1001000 &
b1001000 .
b1001000 7
1)
#770000
0)
#775000
b1001001 &
b1001001 .
b1001001 7
1)
#780000
0)
#785000
b1001010 &
b1001010 .
b1001010 7
1)
#790000
0)
#795000
b1001011 &
b1001011 .
b1001011 7
1)
#800000
0)
#805000
b1001100 &
b1001100 .
b1001100 7
1)
#810000
0)
#815000
b1001101 &
b1001101 .
b1001101 7
1)
#820000
0)
#825000
b1001110 &
b1001110 .
b1001110 7
1)
#830000
0)
#835000
b1001111 &
b1001111 .
b1001111 7
1)
#840000
0)
#845000
b1010000 &
b1010000 .
b1010000 7
1)
#850000
0)
#855000
b1010001 &
b1010001 .
b1010001 7
1)
#860000
0)
#865000
b1010010 &
b1010010 .
b1010010 7
1)
#870000
0)
#875000
b1010011 &
b1010011 .
b1010011 7
1)
#880000
0)
#885000
b1010100 &
b1010100 .
b1010100 7
1)
#890000
0)
#895000
b1010101 &
b1010101 .
b1010101 7
1)
#900000
0)
#905000
b1010110 &
b1010110 .
b1010110 7
1)
#910000
0)
#915000
b1010111 &
b1010111 .
b1010111 7
1)
#920000
0)
#925000
b1011000 &
b1011000 .
b1011000 7
1)
#930000
0)
#935000
b1011001 &
b1011001 .
b1011001 7
1)
#940000
0)
#945000
b1011010 &
b1011010 .
b1011010 7
1)
#950000
0)
#955000
b1011011 &
b1011011 .
b1011011 7
1)
#960000
0)
#965000
b1011100 &
b1011100 .
b1011100 7
1)
#970000
0)
#975000
b1011101 &
b1011101 .
b1011101 7
1)
#980000
0)
#985000
b1011110 &
b1011110 .
b1011110 7
1)
#990000
0)
#995000
b1011111 &
b1011111 .
b1011111 7
1)
#1000000
0)
#1005000
b1100000 &
b1100000 .
b1100000 7
1)
#1010000
0)
#1015000
b1100001 &
b1100001 .
b1100001 7
1)
#1020000
0)
#1025000
b1100010 &
b1100010 .
b1100010 7
1)
#1030000
0)
#1035000
b1100011 &
b1100011 .
b1100011 7
1)
#1040000
0)
#1045000
b1100100 &
b1100100 .
b1100100 7
1)
#1050000
0)
#1055000
b1100101 &
b1100101 .
b1100101 7
1)
#1060000
0)
#1065000
b1100110 &
b1100110 .
b1100110 7
1)
#1070000
0)
#1075000
b1100111 &
b1100111 .
b1100111 7
1)
#1080000
0)
#1085000
b1101000 &
b1101000 .
b1101000 7
1)
#1090000
0)
#1095000
b1101001 &
b1101001 .
b1101001 7
1)
#1100000
0)
#1105000
b1101010 &
b1101010 .
b1101010 7
1)
#1110000
0)
#1115000
b1101011 &
b1101011 .
b1101011 7
1)
#1120000
0)
#1125000
b1101100 &
b1101100 .
b1101100 7
1)
#1130000
0)
#1135000
b1101101 &
b1101101 .
b1101101 7
1)
#1140000
0)
#1145000
b1101110 &
b1101110 .
b1101110 7
1)
#1150000
0)
#1155000
b1101111 &
b1101111 .
b1101111 7
1)
#1160000
0)
#1165000
b1110000 &
b1110000 .
b1110000 7
1)
#1170000
0)
#1175000
b1110001 &
b1110001 .
b1110001 7
1)
#1180000
0)
#1185000
b1110010 &
b1110010 .
b1110010 7
1)
#1190000
0)
#1195000
b1110011 &
b1110011 .
b1110011 7
1)
#1200000
0)
#1205000
b1110100 &
b1110100 .
b1110100 7
1)
#1210000
0)
#1215000
b1110101 &
b1110101 .
b1110101 7
1)
#1220000
0)
#1225000
b1110110 &
b1110110 .
b1110110 7
1)
#1230000
0)
#1235000
b1110111 &
b1110111 .
b1110111 7
1)
#1240000
0)
#1245000
b1111000 &
b1111000 .
b1111000 7
1)
#1250000
0)
#1255000
b1111001 &
b1111001 .
b1111001 7
1)
#1260000
0)
#1265000
b1111010 &
b1111010 .
b1111010 7
1)
#1270000
0)
#1275000
b1111011 &
b1111011 .
b1111011 7
1)
#1280000
0)
#1285000
b1111100 &
b1111100 .
b1111100 7
1)
#1290000
0)
#1295000
b1111101 &
b1111101 .
b1111101 7
1)
#1300000
0)
#1305000
b1111110 &
b1111110 .
b1111110 7
1)
#1310000
0)
#1315000
b1111111 &
b1111111 .
b1111111 7
1)
#1320000
0)
#1325000
b10000000 &
b10000000 .
b10000000 7
1)
#1330000
0)
#1335000
b10000001 &
b10000001 .
b10000001 7
1)
#1340000
0)
#1345000
b10000010 &
b10000010 .
b10000010 7
1)
#1350000
0)
#1355000
b10000011 &
b10000011 .
b10000011 7
1)
#1360000
0)
#1365000
b10000100 &
b10000100 .
b10000100 7
1)
#1370000
0)
#1375000
b10000101 &
b10000101 .
b10000101 7
1)
#1380000
0)
#1385000
b10000110 &
b10000110 .
b10000110 7
1)
#1390000
0)
#1395000
b10000111 &
b10000111 .
b10000111 7
1)
#1400000
0)
#1405000
b10001000 &
b10001000 .
b10001000 7
1)
#1410000
0)
#1415000
b10001001 &
b10001001 .
b10001001 7
1)
#1420000
0)
#1425000
b10001010 &
b10001010 .
b10001010 7
1)
#1430000
0)
#1435000
b10001011 &
b10001011 .
b10001011 7
1)
#1440000
0)
#1445000
b10001100 &
b10001100 .
b10001100 7
1)
#1450000
0)
#1455000
b10001101 &
b10001101 .
b10001101 7
1)
#1460000
0)
#1465000
b10001110 &
b10001110 .
b10001110 7
1)
#1470000
0)
#1475000
b10001111 &
b10001111 .
b10001111 7
1)
#1480000
0)
#1485000
b10010000 &
b10010000 .
b10010000 7
1)
#1490000
0)
#1495000
b10010001 &
b10010001 .
b10010001 7
1)
#1500000
0)
#1505000
b10010010 &
b10010010 .
b10010010 7
1)
#1510000
0)
#1515000
b10010011 &
b10010011 .
b10010011 7
1)
#1520000
0)
#1525000
b10010100 &
b10010100 .
b10010100 7
1)
#1530000
0)
#1535000
b10010101 &
b10010101 .
b10010101 7
1)
#1540000
0)
#1545000
b10010110 &
b10010110 .
b10010110 7
1)
#1550000
0)
#1555000
b10010111 &
b10010111 .
b10010111 7
1)
#1560000
0)
#1565000
b10011000 &
b10011000 .
b10011000 7
1)
#1570000
0)
#1575000
b10011001 &
b10011001 .
b10011001 7
1)
#1580000
0)
#1585000
b10011010 &
b10011010 .
b10011010 7
1)
#1590000
0)
#1595000
b10011011 &
b10011011 .
b10011011 7
1)
#1600000
0)
#1605000
b10011100 &
b10011100 .
b10011100 7
1)
#1610000
0)
#1615000
b10011101 &
b10011101 .
b10011101 7
1)
#1620000
0)
#1625000
b10011110 &
b10011110 .
b10011110 7
1)
#1630000
0)
#1635000
b10011111 &
b10011111 .
b10011111 7
1)
#1640000
0)
#1645000
b10100000 &
b10100000 .
b10100000 7
1)
#1650000
0)
#1655000
b10100001 &
b10100001 .
b10100001 7
1)
#1660000
0)
#1665000
b10100010 &
b10100010 .
b10100010 7
1)
#1670000
0)
#1675000
b10100011 &
b10100011 .
b10100011 7
1)
#1680000
0)
#1685000
b10100100 &
b10100100 .
b10100100 7
1)
#1690000
0)
#1695000
b10100101 &
b10100101 .
b10100101 7
1)
#1700000
0)
#1705000
b10100110 &
b10100110 .
b10100110 7
1)
#1710000
0)
#1715000
b10100111 &
b10100111 .
b10100111 7
1)
#1720000
0)
#1725000
b10101000 &
b10101000 .
b10101000 7
1)
#1730000
0)
#1735000
b10101001 &
b10101001 .
b10101001 7
1)
#1740000
0)
#1745000
b10101010 &
b10101010 .
b10101010 7
1)
#1750000
0)
#1755000
b10101011 &
b10101011 .
b10101011 7
1)
#1760000
0)
#1765000
b10101100 &
b10101100 .
b10101100 7
1)
#1770000
0)
#1775000
b10101101 &
b10101101 .
b10101101 7
1)
#1780000
0)
#1785000
b10101110 &
b10101110 .
b10101110 7
1)
#1790000
0)
#1795000
b10101111 &
b10101111 .
b10101111 7
1)
#1800000
0)
#1805000
b10110000 &
b10110000 .
b10110000 7
1)
#1810000
0)
#1815000
b10110001 &
b10110001 .
b10110001 7
1)
#1820000
0)
#1825000
b10110010 &
b10110010 .
b10110010 7
1)
#1830000
0)
#1835000
b10110011 &
b10110011 .
b10110011 7
1)
#1840000
0)
#1845000
b10110100 &
b10110100 .
b10110100 7
1)
#1850000
0)
#1855000
b10110101 &
b10110101 .
b10110101 7
1)
#1860000
0)
#1865000
b10110110 &
b10110110 .
b10110110 7
1)
#1870000
0)
#1875000
b10110111 &
b10110111 .
b10110111 7
1)
#1880000
0)
#1885000
b10111000 &
b10111000 .
b10111000 7
1)
#1890000
0)
#1895000
b10111001 &
b10111001 .
b10111001 7
1)
#1900000
0)
#1905000
b10111010 &
b10111010 .
b10111010 7
1)
#1910000
0)
#1915000
b10111011 &
b10111011 .
b10111011 7
1)
#1920000
0)
#1925000
b10111100 &
b10111100 .
b10111100 7
1)
#1930000
0)
#1935000
b10111101 &
b10111101 .
b10111101 7
1)
#1940000
0)
#1945000
b10111110 &
b10111110 .
b10111110 7
1)
#1950000
0)
#1955000
b10111111 &
b10111111 .
b10111111 7
1)
#1960000
0)
#1965000
b11000000 &
b11000000 .
b11000000 7
1)
#1970000
0)
#1975000
b11000001 &
b11000001 .
b11000001 7
1)
#1980000
0)
#1985000
b11000010 &
b11000010 .
b11000010 7
1)
#1990000
0)
#1995000
b11000011 &
b11000011 .
b11000011 7
1)
#2000000
0)
#2005000
b11000100 &
b11000100 .
b11000100 7
1)
#2010000
0)
#2015000
b11000101 &
b11000101 .
b11000101 7
1)
#2020000
0)
#2025000
b11000110 &
b11000110 .
b11000110 7
1)
#2030000
0)
#2035000
b11000111 &
b11000111 .
b11000111 7
1)
#2040000
0)
#2045000
b11001000 &
b11001000 .
b11001000 7
1)
#2050000
0)
#2055000
b11001001 &
b11001001 .
b11001001 7
1)
#2060000
0)
#2065000
b11001010 &
b11001010 .
b11001010 7
1)
#2070000
0)
#2075000
b11001011 &
b11001011 .
b11001011 7
1)
#2080000
0)
#2085000
b11001100 &
b11001100 .
b11001100 7
1)
#2090000
0)
#2095000
b11001101 &
b11001101 .
b11001101 7
1)
#2100000
0)
#2105000
b11001110 &
b11001110 .
b11001110 7
1)
#2110000
0)
#2115000
b11001111 &
b11001111 .
b11001111 7
1)
#2120000
0)
#2125000
b11010000 &
b11010000 .
b11010000 7
1)
#2130000
0)
#2135000
b11010001 &
b11010001 .
b11010001 7
1)
#2140000
0)
#2145000
b11010010 &
b11010010 .
b11010010 7
1)
#2150000
0)
#2155000
b11010011 &
b11010011 .
b11010011 7
1)
#2160000
0)
#2165000
b11010100 &
b11010100 .
b11010100 7
1)
#2170000
0)
#2175000
b11010101 &
b11010101 .
b11010101 7
1)
#2180000
0)
#2185000
b11010110 &
b11010110 .
b11010110 7
1)
#2190000
0)
#2195000
b11010111 &
b11010111 .
b11010111 7
1)
#2200000
0)
#2205000
b11011000 &
b11011000 .
b11011000 7
1)
#2210000
0)
#2215000
b11011001 &
b11011001 .
b11011001 7
1)
#2220000
0)
#2225000
b11011010 &
b11011010 .
b11011010 7
1)
#2230000
0)
#2235000
b11011011 &
b11011011 .
b11011011 7
1)
#2240000
0)
#2245000
b11011100 &
b11011100 .
b11011100 7
1)
#2250000
0)
#2255000
b11011101 &
b11011101 .
b11011101 7
1)
#2260000
0)
#2265000
b11011110 &
b11011110 .
b11011110 7
1)
#2270000
0)
#2275000
b11011111 &
b11011111 .
b11011111 7
1)
#2280000
0)
#2285000
b11100000 &
b11100000 .
b11100000 7
1)
#2290000
0)
#2295000
b11100001 &
b11100001 .
b11100001 7
1)
#2300000
0)
#2305000
b11100010 &
b11100010 .
b11100010 7
1)
#2310000
0)
#2315000
b11100011 &
b11100011 .
b11100011 7
1)
#2320000
0)
#2325000
b11100100 &
b11100100 .
b11100100 7
1)
#2330000
0)
#2335000
b11100101 &
b11100101 .
b11100101 7
1)
#2340000
0)
#2345000
b11100110 &
b11100110 .
b11100110 7
1)
#2350000
0)
#2355000
b11100111 &
b11100111 .
b11100111 7
1)
#2360000
0)
#2365000
b11101000 &
b11101000 .
b11101000 7
1)
#2370000
0)
#2375000
b11101001 &
b11101001 .
b11101001 7
1)
#2380000
0)
#2385000
b11101010 &
b11101010 .
b11101010 7
1)
#2390000
0)
#2395000
b11101011 &
b11101011 .
b11101011 7
1)
#2400000
0)
#2405000
b11101100 &
b11101100 .
b11101100 7
1)
#2410000
0)
#2415000
b11101101 &
b11101101 .
b11101101 7
1)
#2420000
0)
#2425000
b11101110 &
b11101110 .
b11101110 7
1)
#2430000
0)
#2435000
b11101111 &
b11101111 .
b11101111 7
1)
#2440000
0)
#2445000
b11110000 &
b11110000 .
b11110000 7
1)
#2450000
0)
#2455000
b11110001 &
b11110001 .
b11110001 7
1)
#2460000
0)
#2465000
b11110010 &
b11110010 .
b11110010 7
1)
#2470000
0)
#2475000
b11110011 &
b11110011 .
b11110011 7
1)
#2480000
0)
#2485000
b11110100 &
b11110100 .
b11110100 7
1)
#2490000
0)
#2495000
b11110101 &
b11110101 .
b11110101 7
1)
#2500000
0)
#2505000
b11110110 &
b11110110 .
b11110110 7
1)
#2510000
0)
#2515000
b11110111 &
b11110111 .
b11110111 7
1)
#2520000
0)
#2525000
b11111000 &
b11111000 .
b11111000 7
1)
#2530000
0)
#2535000
b11111001 &
b11111001 .
b11111001 7
1)
#2540000
0)
#2545000
b11111010 &
b11111010 .
b11111010 7
1)
#2550000
0)
#2555000
b11111011 &
b11111011 .
b11111011 7
1)
#2560000
0)
#2565000
b11111100 &
b11111100 .
b11111100 7
1)
#2570000
0)
#2575000
b11111101 &
b11111101 .
b11111101 7
1)
#2580000
0)
